pymodaq_plugins_orsay/__init__.py
pymodaq_plugins_orsay/version.py
pymodaq_plugins_orsay/daq_move_plugins/__init__.py
pymodaq_plugins_orsay/daq_move_plugins/daq_move_OrsaySTEM.py
pymodaq_plugins_orsay/daq_viewer_plugins/__init__.py
pymodaq_plugins_orsay/daq_viewer_plugins/plugins_0D/__init__.py
pymodaq_plugins_orsay/daq_viewer_plugins/plugins_1D/__init__.py
pymodaq_plugins_orsay/daq_viewer_plugins/plugins_2D/__init__.py
pymodaq_plugins_orsay/daq_viewer_plugins/plugins_2D/daq_2Dviewer_OrsayCamera.py
pymodaq_plugins_orsay/daq_viewer_plugins/plugins_2D/daq_2Dviewer_OrsaySTEM.py
pymodaq_plugins_orsay/daq_viewer_plugins/plugins_ND/__init__.py
pymodaq_plugins_orsay/hardware/__init__.py
pymodaq_plugins_orsay/hardware/STEM/Cameras.dll
pymodaq_plugins_orsay/hardware/STEM/ClientGun.dll
pymodaq_plugins_orsay/hardware/STEM/Connection.dll
pymodaq_plugins_orsay/hardware/STEM/CredoClient.dll
pymodaq_plugins_orsay/hardware/STEM/OrsayCameraDevice.py
pymodaq_plugins_orsay/hardware/STEM/OrsayDevice.py
pymodaq_plugins_orsay/hardware/STEM/OrsayHardwareProxy.py
pymodaq_plugins_orsay/hardware/STEM/PythonCamerademo.py
pymodaq_plugins_orsay/hardware/STEM/PythonScanDemo.py
pymodaq_plugins_orsay/hardware/STEM/STEMEELSCCD.dll
pymodaq_plugins_orsay/hardware/STEM/STEMSerial.dll
pymodaq_plugins_orsay/hardware/STEM/STEMSerialLib.dll
pymodaq_plugins_orsay/hardware/STEM/Scan.dll
pymodaq_plugins_orsay/hardware/STEM/SpectroCL.dll
pymodaq_plugins_orsay/hardware/STEM/Stepper.dll
pymodaq_plugins_orsay/hardware/STEM/__init__.py
pymodaq_plugins_orsay/hardware/STEM/orsaycamera.py
pymodaq_plugins_orsay/hardware/STEM/orsayscan.py
pymodaq_plugins_orsay/hardware/STEM/orsayscan_position.py
pymodaq_plugins_orsay/hardware/STEM/test.py
pymodaq_plugins_orsay-0.0.1.dist-info/LICENSE
pymodaq_plugins_orsay-0.0.1.dist-info/METADATA
pymodaq_plugins_orsay-0.0.1.dist-info/WHEEL
pymodaq_plugins_orsay-0.0.1.dist-info/entry_points.txt
pymodaq_plugins_orsay-0.0.1.dist-info/top_level.txt
pymodaq_plugins_orsay-0.0.1.dist-info/RECORD
