Metadata-Version: 2.1
Name: pymodaq-plugins-orsay
Version: 0.0.1
Summary: Hardware plugins for PyMoDAQ using the NiDAQmx framework (pydaqmx wrapper)
Home-page: https://github.com/CEMES-CNRS/pymodaq_plugins_orsay
Author: Sébastien Weber
Author-email: sebastien.weber@cemes.fr
License: CECILL B
Platform: UNKNOWN
Classifier: Programming Language :: Python :: 3
Classifier: Development Status :: 5 - Production/Stable
Classifier: Environment :: Other Environment
Classifier: Intended Audience :: Science/Research
Classifier: Topic :: Scientific/Engineering :: Human Machine Interfaces
Classifier: Topic :: Scientific/Engineering :: Visualization
Classifier: License :: CeCILL-B Free Software License Agreement (CECILL-B)
Classifier: Operating System :: OS Independent
Classifier: Topic :: Software Development :: Libraries :: Python Modules
Classifier: Topic :: Software Development :: User Interfaces
Requires-Dist: pymodaq (>=2.0)
